apertif/__init__.py
apertif-0.0.1.dist-info/METADATA
apertif-0.0.1.dist-info/WHEEL
apertif-0.0.1.dist-info/top_level.txt
apertif-0.0.1.dist-info/RECORD
